[
    {
        "Nom du fichier": "Script3.py",
        "chemin_complet": "C:\\\\Users\\\\e2400575\\\\PycharmProjects\\\\SAE_traiter_donnees\\\\Script3.py",
        "taille_octets": 10926,
        "derniere_modification": "2025-01-23 10:47:45"
    },
    {
        "Nom du fichier": "Script1.py",
        "chemin_complet": "C:\\\\Users\\\\e2400575\\\\PycharmProjects\\\\SAE_traiter_donnees\\\\Script1.py",
        "taille_octets": 5038,
        "derniere_modification": "2025-01-23 10:31:43"
    },
    {
        "Nom du fichier": "pre-rebase.sample",
        "chemin_complet": "C:\\\\Users\\\\e2400575\\\\PycharmProjects\\\\SAE_traiter_donnees\\\\.git\\\\hooks\\\\pre-rebase.sample",
        "taille_octets": 4898,
        "derniere_modification": "2025-01-23 10:23:33"
    },
    {
        "Nom du fichier": "workspace.xml",
        "chemin_complet": "C:\\\\Users\\\\e2400575\\\\PycharmProjects\\\\SAE_traiter_donnees\\\\.idea\\\\workspace.xml",
        "taille_octets": 4832,
        "derniere_modification": "2025-01-23 10:35:48"
    },
    {
        "Nom du fichier": "fsmonitor-watchman.sample",
        "chemin_complet": "C:\\\\Users\\\\e2400575\\\\PycharmProjects\\\\SAE_traiter_donnees\\\\.git\\\\hooks\\\\fsmonitor-watchman.sample",
        "taille_octets": 4726,
        "derniere_modification": "2025-01-23 10:23:33"
    },
    {
        "Nom du fichier": "70340bd05b134160b374586de9bd18732a38e8",
        "chemin_complet": "C:\\\\Users\\\\e2400575\\\\PycharmProjects\\\\SAE_traiter_donnees\\\\.git\\\\objects\\\\74\\\\70340bd05b134160b374586de9bd18732a38e8",
        "taille_octets": 3810,
        "derniere_modification": "2025-01-23 10:25:35"
    },
    {
        "Nom du fichier": "update.sample",
        "chemin_complet": "C:\\\\Users\\\\e2400575\\\\PycharmProjects\\\\SAE_traiter_donnees\\\\.git\\\\hooks\\\\update.sample",
        "taille_octets": 3650,
        "derniere_modification": "2025-01-23 10:23:33"
    },
    {
        "Nom du fichier": "push-to-checkout.sample",
        "chemin_complet": "C:\\\\Users\\\\e2400575\\\\PycharmProjects\\\\SAE_traiter_donnees\\\\.git\\\\hooks\\\\push-to-checkout.sample",
        "taille_octets": 2783,
        "derniere_modification": "2025-01-23 10:23:33"
    },
    {
        "Nom du fichier": "sendemail-validate.sample",
        "chemin_complet": "C:\\\\Users\\\\e2400575\\\\PycharmProjects\\\\SAE_traiter_donnees\\\\.git\\\\hooks\\\\sendemail-validate.sample",
        "taille_octets": 2308,
        "derniere_modification": "2025-01-23 10:23:33"
    },
    {
        "Nom du fichier": "2f962d337200b0124f0f3270cedb3e61364be1",
        "chemin_complet": "C:\\\\Users\\\\e2400575\\\\PycharmProjects\\\\SAE_traiter_donnees\\\\.git\\\\objects\\\\64\\\\2f962d337200b0124f0f3270cedb3e61364be1",
        "taille_octets": 1726,
        "derniere_modification": "2025-01-23 10:25:35"
    }
]